randomcontent/__init__.py
randomcontent/generators/__init__.py
randomcontent/generators/identifier_generator.py
randomcontent/generators/number_generator.py
randomcontent/generators/structured_generator.py
randomcontent/generators/text_generator.py
randomcontent/utils/__init__.py
randomcontent/utils/data_utils.py
randomcontent/utils/template_utils.py
tests/__init__.py
tests/test_generators.py
randomcontentgenerator-0.0.1.dist-info/LICENSE.txt
randomcontentgenerator-0.0.1.dist-info/METADATA
randomcontentgenerator-0.0.1.dist-info/WHEEL
randomcontentgenerator-0.0.1.dist-info/top_level.txt
randomcontentgenerator-0.0.1.dist-info/RECORD
